synology_dsm/__init__.py
synology_dsm/api/__init__.py
synology_dsm/api/core/__init__.py
synology_dsm/api/core/security.py
synology_dsm/api/core/share.py
synology_dsm/api/core/system.py
synology_dsm/api/core/upgrade.py
synology_dsm/api/core/utilization.py
synology_dsm/api/download_station/__init__.py
synology_dsm/api/download_station/task.py
synology_dsm/api/dsm/__init__.py
synology_dsm/api/dsm/information.py
synology_dsm/api/dsm/network.py
synology_dsm/api/storage/__init__.py
synology_dsm/api/storage/storage.py
synology_dsm/api/surveillance_station/__init__.py
synology_dsm/api/surveillance_station/camera.py
synology_dsm/api/surveillance_station/const.py
synology_dsm/const.py
synology_dsm/exceptions.py
synology_dsm/helpers.py
synology_dsm/synology_dsm.py
synologydsm_api-1.0.2.dist-info/entry_points.txt
synologydsm_api-1.0.2.dist-info/LICENSE.txt
synologydsm_api-1.0.2.dist-info/WHEEL
synologydsm_api-1.0.2.dist-info/METADATA
synologydsm_api-1.0.2.dist-info/RECORD
