Metadata-Version: 2.1
Name: synologydsm-api
Version: 1.0.2
Summary: Python API for communication with Synology DSM
Home-page: https://github.com/hacf-fr/synologydsm-api
License: MIT
Keywords: synology-dsm,synology
Author: Quentin POLLET (Quentame)
Requires-Python: >=3.7.0,<4.0.0
Classifier: Development Status :: 5 - Production/Stable
Classifier: Intended Audience :: Developers
Classifier: License :: OSI Approved :: MIT License
Classifier: Operating System :: OS Independent
Classifier: Programming Language :: Python
Classifier: Programming Language :: Python :: 3
Classifier: Programming Language :: Python :: 3 :: Only
Classifier: Programming Language :: Python :: 3.7
Classifier: Programming Language :: Python :: 3.8
Classifier: Programming Language :: Python :: 3.9
Classifier: Topic :: Software Development :: Libraries
Requires-Dist: requests (>=2.24.0,<3.0.0)
Requires-Dist: urllib3 (>=1.25.10,<2.0.0)
Project-URL: Changelog, https://github.com/hacf-fr/synologydsm-api/releases
Project-URL: Documentation, https://synologydsm-api.readthedocs.io
Project-URL: Repository, https://github.com/hacf-fr/synologydsm-api
